[
  {
    "Type": "GDSEnemyPlacementFormation",
    "Name": "GDSEnemyPlacementFormation",
    "Class": "UScriptClass'GDSEnemyPlacementFormation'",
    "Flags": "RF_Public | RF_Standalone | RF_Transactional | RF_WasLoaded | RF_LoadCompleted",
    "Properties": {
      "m_dataMap": [
        {
          "Key": "enm_form_0001",
          "Value": {
            "ID": "enm_form_0001",
            "Placement": [
              {
                "X": 0.0,
                "Y": 1.0,
                "Z": 0.0,
                "W": 0.0
              },
              {
                "X": 1.0,
                "Y": -1.0,
                "Z": 0.0,
                "W": 0.0
              },
              {
                "X": -1.0,
                "Y": -1.0,
                "Z": 0.0,
                "W": 0.0
              }
            ]
          }
        },
        {
          "Key": "enm_form_0002",
          "Value": {
            "ID": "enm_form_0002",
            "Placement": [
              {
                "X": 1.0,
                "Y": 1.0,
                "Z": 0.0,
                "W": 0.0
              },
              {
                "X": 1.0,
                "Y": -1.0,
                "Z": 0.0,
                "W": 0.0
              },
              {
                "X": -1.0,
                "Y": 1.0,
                "Z": 0.0,
                "W": 0.0
              },
              {
                "X": -1.0,
                "Y": -1.0,
                "Z": 0.0,
                "W": 0.0
              }
            ]
          }
        },
        {
          "Key": "enm_form_01_01",
          "Value": {
            "ID": "enm_form_01_01",
            "Placement": [
              {
                "X": 0.0,
                "Y": 1.0,
                "Z": 0.0,
                "W": 180.0
              }
            ]
          }
        },
        {
          "Key": "enm_form_01_02",
          "Value": {
            "ID": "enm_form_01_02",
            "Placement": [
              {
                "X": 0.0,
                "Y": 2.0,
                "Z": 0.0,
                "W": 180.0
              }
            ]
          }
        },
        {
          "Key": "enm_form_02_01",
          "Value": {
            "ID": "enm_form_02_01",
            "Placement": [
              {
                "X": 1.0,
                "Y": 1.0,
                "Z": 0.0,
                "W": 180.0
              },
              {
                "X": -1.0,
                "Y": 1.0,
                "Z": 0.0,
                "W": 180.0
              }
            ]
          }
        },
        {
          "Key": "enm_form_02_02",
          "Value": {
            "ID": "enm_form_02_02",
            "Placement": [
              {
                "X": 0.0,
                "Y": 1.0,
                "Z": 0.0,
                "W": 180.0
              },
              {
                "X": 0.0,
                "Y": 2.0,
                "Z": 0.0,
                "W": 180.0
              }
            ]
          }
        },
        {
          "Key": "enm_form_02_03",
          "Value": {
            "ID": "enm_form_02_03",
            "Placement": [
              {
                "X": 1.0,
                "Y": 0.0,
                "Z": 0.0,
                "W": -90.0
              },
              {
                "X": -1.0,
                "Y": 0.0,
                "Z": 0.0,
                "W": 90.0
              }
            ]
          }
        },
        {
          "Key": "enm_form_02_04",
          "Value": {
            "ID": "enm_form_02_04",
            "Placement": [
              {
                "X": 1.0,
                "Y": 1.0,
                "Z": 0.0,
                "W": 90.0
              },
              {
                "X": -1.0,
                "Y": 1.0,
                "Z": 0.0,
                "W": 90.0
              }
            ]
          }
        },
        {
          "Key": "enm_form_03_01",
          "Value": {
            "ID": "enm_form_03_01",
            "Placement": [
              {
                "X": 0.0,
                "Y": 1.0,
                "Z": 0.0,
                "W": 180.0
              },
              {
                "X": 1.0,
                "Y": -1.0,
                "Z": 0.0,
                "W": -45.0
              },
              {
                "X": -1.0,
                "Y": -1.0,
                "Z": 0.0,
                "W": 45.0
              }
            ]
          }
        },
        {
          "Key": "enm_form_03_02",
          "Value": {
            "ID": "enm_form_03_02",
            "Placement": [
              {
                "X": 0.0,
                "Y": 1.0,
                "Z": 0.0,
                "W": 180.0
              },
              {
                "X": 1.0,
                "Y": 1.0,
                "Z": 0.0,
                "W": -135.0
              },
              {
                "X": -1.0,
                "Y": 1.0,
                "Z": 0.0,
                "W": 135.0
              }
            ]
          }
        },
        {
          "Key": "enm_form_03_03",
          "Value": {
            "ID": "enm_form_03_03",
            "Placement": [
              {
                "X": 0.0,
                "Y": 2.0,
                "Z": 0.0,
                "W": 180.0
              },
              {
                "X": 1.0,
                "Y": 1.0,
                "Z": 0.0,
                "W": 180.0
              },
              {
                "X": -1.0,
                "Y": 1.0,
                "Z": 0.0,
                "W": 180.0
              }
            ]
          }
        },
        {
          "Key": "enm_form_03_04",
          "Value": {
            "ID": "enm_form_03_04",
            "Placement": [
              {
                "X": 0.0,
                "Y": 2.0,
                "Z": 0.0,
                "W": 90.0
              },
              {
                "X": 1.0,
                "Y": 1.0,
                "Z": 0.0,
                "W": 90.0
              },
              {
                "X": -1.0,
                "Y": 1.0,
                "Z": 0.0,
                "W": 90.0
              }
            ]
          }
        },
        {
          "Key": "enm_form_04_01",
          "Value": {
            "ID": "enm_form_04_01",
            "Placement": [
              {
                "X": 1.0,
                "Y": 1.0,
                "Z": 0.0,
                "W": -135.0
              },
              {
                "X": 1.0,
                "Y": -1.0,
                "Z": 0.0,
                "W": 135.0
              },
              {
                "X": -1.0,
                "Y": 1.0,
                "Z": 0.0,
                "W": -45.0
              },
              {
                "X": -1.0,
                "Y": -1.0,
                "Z": 0.0,
                "W": 45.0
              }
            ]
          }
        },
        {
          "Key": "enm_form_04_02",
          "Value": {
            "ID": "enm_form_04_02",
            "Placement": [
              {
                "X": 1.0,
                "Y": 1.0,
                "Z": 0.0,
                "W": 180.0
              },
              {
                "X": 1.0,
                "Y": 2.0,
                "Z": 0.0,
                "W": -135.0
              },
              {
                "X": -1.0,
                "Y": 1.0,
                "Z": 0.0,
                "W": 180.0
              },
              {
                "X": -1.0,
                "Y": 2.0,
                "Z": 0.0,
                "W": 135.0
              }
            ]
          }
        },
        {
          "Key": "enm_form_04_03",
          "Value": {
            "ID": "enm_form_04_03",
            "Placement": [
              {
                "X": 1.0,
                "Y": 1.0,
                "Z": 0.0,
                "W": 90.0
              },
              {
                "X": 1.0,
                "Y": 2.0,
                "Z": 0.0,
                "W": 90.0
              },
              {
                "X": -1.0,
                "Y": 1.0,
                "Z": 0.0,
                "W": 90.0
              },
              {
                "X": -1.0,
                "Y": 2.0,
                "Z": 0.0,
                "W": 90.0
              }
            ]
          }
        },
        {
          "Key": "enm_form_05_01",
          "Value": {
            "ID": "enm_form_05_01",
            "Placement": [
              {
                "X": 0.0,
                "Y": 2.0,
                "Z": 0.0,
                "W": 180.0
              },
              {
                "X": 2.0,
                "Y": 0.0,
                "Z": 0.0,
                "W": -90.0
              },
              {
                "X": 1.0,
                "Y": -2.0,
                "Z": 0.0,
                "W": -45.0
              },
              {
                "X": -1.0,
                "Y": -2.0,
                "Z": 0.0,
                "W": 45.0
              },
              {
                "X": -2.0,
                "Y": 0.0,
                "Z": 0.0,
                "W": 90.0
              }
            ]
          }
        },
        {
          "Key": "enm_form_05_02",
          "Value": {
            "ID": "enm_form_05_02",
            "Placement": [
              {
                "X": 0.0,
                "Y": 1.0,
                "Z": 0.0,
                "W": 180.0
              },
              {
                "X": 1.0,
                "Y": 2.0,
                "Z": 0.0,
                "W": 180.0
              },
              {
                "X": 2.0,
                "Y": 1.0,
                "Z": 0.0,
                "W": -135.0
              },
              {
                "X": -1.0,
                "Y": 2.0,
                "Z": 0.0,
                "W": 180.0
              },
              {
                "X": -2.0,
                "Y": 1.0,
                "Z": 0.0,
                "W": 135.0
              }
            ]
          }
        },
        {
          "Key": "enm_form_05_03",
          "Value": {
            "ID": "enm_form_05_03",
            "Placement": [
              {
                "X": 0.0,
                "Y": 2.0,
                "Z": 0.0,
                "W": 90.0
              },
              {
                "X": 2.0,
                "Y": 4.0,
                "Z": 0.0,
                "W": 90.0
              },
              {
                "X": 4.0,
                "Y": 2.0,
                "Z": 0.0,
                "W": 90.0
              },
              {
                "X": -2.0,
                "Y": 4.0,
                "Z": 0.0,
                "W": 90.0
              },
              {
                "X": -4.0,
                "Y": 2.0,
                "Z": 0.0,
                "W": 90.0
              }
            ]
          }
        },
        {
          "Key": "enm_form_06_01",
          "Value": {
            "ID": "enm_form_06_01",
            "Placement": [
              {
                "X": 0.0,
                "Y": 1.0,
                "Z": 0.0,
                "W": 180.0
              },
              {
                "X": 1.0,
                "Y": 1.0,
                "Z": 0.0,
                "W": -135.0
              },
              {
                "X": -1.0,
                "Y": 1.0,
                "Z": 0.0,
                "W": -45.0
              },
              {
                "X": 0.0,
                "Y": -1.0,
                "Z": 0.0,
                "W": 0.0
              },
              {
                "X": -1.0,
                "Y": -1.0,
                "Z": 0.0,
                "W": 45.0
              },
              {
                "X": -1.0,
                "Y": 1.0,
                "Z": 0.0,
                "W": 135.0
              }
            ]
          }
        },
        {
          "Key": "enm_form_06_02",
          "Value": {
            "ID": "enm_form_06_02",
            "Placement": [
              {
                "X": 0.0,
                "Y": 1.0,
                "Z": 0.0,
                "W": 180.0
              },
              {
                "X": 1.0,
                "Y": 1.0,
                "Z": 0.0,
                "W": 180.0
              },
              {
                "X": -1.0,
                "Y": 1.0,
                "Z": 0.0,
                "W": 180.0
              },
              {
                "X": 0.0,
                "Y": -1.0,
                "Z": 0.0,
                "W": 0.0
              },
              {
                "X": 1.0,
                "Y": -1.0,
                "Z": 0.0,
                "W": 0.0
              },
              {
                "X": -1.0,
                "Y": -1.0,
                "Z": 0.0,
                "W": 0.0
              }
            ]
          }
        },
        {
          "Key": "enm_form_07_01",
          "Value": {
            "ID": "enm_form_07_01",
            "Placement": [
              {
                "X": 0.0,
                "Y": 1.0,
                "Z": 0.0,
                "W": 180.0
              },
              {
                "X": 1.0,
                "Y": 1.0,
                "Z": 0.0,
                "W": -135.0
              },
              {
                "X": 2.0,
                "Y": 0.0,
                "Z": 0.0,
                "W": -90.0
              },
              {
                "X": 1.0,
                "Y": -2.0,
                "Z": 0.0,
                "W": -45.0
              },
              {
                "X": -1.0,
                "Y": -2.0,
                "Z": 0.0,
                "W": 45.0
              },
              {
                "X": -2.0,
                "Y": 0.0,
                "Z": 0.0,
                "W": 90.0
              },
              {
                "X": -1.0,
                "Y": -1.0,
                "Z": 0.0,
                "W": 135.0
              }
            ]
          }
        },
        {
          "Key": "enm_form_07_02",
          "Value": {
            "ID": "enm_form_07_02",
            "Placement": [
              {
                "X": 1.0,
                "Y": 2.0,
                "Z": 0.0,
                "W": 180.0
              },
              {
                "X": 2.0,
                "Y": 1.0,
                "Z": 0.0,
                "W": 180.0
              },
              {
                "X": -1.0,
                "Y": 2.0,
                "Z": 0.0,
                "W": 180.0
              },
              {
                "X": -2.0,
                "Y": 1.0,
                "Z": 0.0,
                "W": 180.0
              },
              {
                "X": 1.0,
                "Y": -1.0,
                "Z": 0.0,
                "W": 0.0
              },
              {
                "X": 0.0,
                "Y": -1.0,
                "Z": 0.0,
                "W": 0.0
              },
              {
                "X": -1.0,
                "Y": -1.0,
                "Z": 0.0,
                "W": 0.0
              }
            ]
          }
        },
        {
          "Key": "enm_form_08_01",
          "Value": {
            "ID": "enm_form_08_01",
            "Placement": [
              {
                "X": 0.0,
                "Y": 1.0,
                "Z": 0.0,
                "W": 180.0
              },
              {
                "X": 1.0,
                "Y": 1.0,
                "Z": 0.0,
                "W": -135.0
              },
              {
                "X": 1.0,
                "Y": 0.0,
                "Z": 0.0,
                "W": -90.0
              },
              {
                "X": 1.0,
                "Y": -1.0,
                "Z": 0.0,
                "W": -45.0
              },
              {
                "X": 0.0,
                "Y": -1.0,
                "Z": 0.0,
                "W": 0.0
              },
              {
                "X": -1.0,
                "Y": -1.0,
                "Z": 0.0,
                "W": 45.0
              },
              {
                "X": -1.0,
                "Y": 0.0,
                "Z": 0.0,
                "W": 90.0
              },
              {
                "X": -1.0,
                "Y": 1.0,
                "Z": 0.0,
                "W": 135.0
              }
            ]
          }
        },
        {
          "Key": "enm_form_08_02",
          "Value": {
            "ID": "enm_form_08_02",
            "Placement": [
              {
                "X": 1.0,
                "Y": 2.0,
                "Z": 0.0,
                "W": -150.0
              },
              {
                "X": 2.0,
                "Y": 1.0,
                "Z": 0.0,
                "W": -120.0
              },
              {
                "X": 2.0,
                "Y": -1.0,
                "Z": 0.0,
                "W": -60.0
              },
              {
                "X": 1.0,
                "Y": -2.0,
                "Z": 0.0,
                "W": -30.0
              },
              {
                "X": -1.0,
                "Y": 2.0,
                "Z": 0.0,
                "W": 30.0
              },
              {
                "X": -2.0,
                "Y": -1.0,
                "Z": 0.0,
                "W": 60.0
              },
              {
                "X": -2.0,
                "Y": 1.0,
                "Z": 0.0,
                "W": 120.0
              },
              {
                "X": -1.0,
                "Y": 2.0,
                "Z": 0.0,
                "W": 150.0
              }
            ]
          }
        },
        {
          "Key": "enm_form_08_03",
          "Value": {
            "ID": "enm_form_08_03",
            "Placement": [
              {
                "X": 1.0,
                "Y": 1.0,
                "Z": 0.0,
                "W": 180.0
              },
              {
                "X": 2.0,
                "Y": 1.0,
                "Z": 0.0,
                "W": 180.0
              },
              {
                "X": -1.0,
                "Y": 1.0,
                "Z": 0.0,
                "W": 180.0
              },
              {
                "X": -2.0,
                "Y": 1.0,
                "Z": 0.0,
                "W": 180.0
              },
              {
                "X": 1.0,
                "Y": -1.0,
                "Z": 0.0,
                "W": 0.0
              },
              {
                "X": 2.0,
                "Y": -1.0,
                "Z": 0.0,
                "W": 0.0
              },
              {
                "X": -1.0,
                "Y": -1.0,
                "Z": 0.0,
                "W": 0.0
              },
              {
                "X": -2.0,
                "Y": -1.0,
                "Z": 0.0,
                "W": 0.0
              }
            ]
          }
        },
        {
          "Key": "enm_form_03_arena",
          "Value": {
            "ID": "enm_form_03_arena",
            "Placement": [
              {
                "X": 0.0,
                "Y": 2.0,
                "Z": 0.0,
                "W": -90.0
              },
              {
                "X": 1.0,
                "Y": 1.0,
                "Z": 0.0,
                "W": -90.0
              },
              {
                "X": -1.0,
                "Y": 1.0,
                "Z": 0.0,
                "W": -90.0
              }
            ]
          }
        },
        {
          "Key": "enm_form_04_arena",
          "Value": {
            "ID": "enm_form_04_arena",
            "Placement": [
              {
                "X": 0.0,
                "Y": 4.0,
                "Z": 0.0,
                "W": -90.0
              },
              {
                "X": 0.0,
                "Y": 2.0,
                "Z": 0.0,
                "W": -90.0
              },
              {
                "X": 2.0,
                "Y": 2.0,
                "Z": 0.0,
                "W": -90.0
              },
              {
                "X": -2.0,
                "Y": 2.0,
                "Z": 0.0,
                "W": -90.0
              }
            ]
          }
        },
        {
          "Key": "enm_form_04_arena_02",
          "Value": {
            "ID": "enm_form_04_arena_02",
            "Placement": [
              {
                "X": 1.0,
                "Y": 3.0,
                "Z": 0.0,
                "W": -90.0
              },
              {
                "X": 2.0,
                "Y": 2.0,
                "Z": 0.0,
                "W": -90.0
              },
              {
                "X": -1.0,
                "Y": 3.0,
                "Z": 0.0,
                "W": -90.0
              },
              {
                "X": -2.0,
                "Y": 2.0,
                "Z": 0.0,
                "W": -90.0
              }
            ]
          }
        },
        {
          "Key": "enm_form_05_arena",
          "Value": {
            "ID": "enm_form_05_arena",
            "Placement": [
              {
                "X": 0.0,
                "Y": 4.0,
                "Z": 0.0,
                "W": -90.0
              },
              {
                "X": 1.0,
                "Y": 3.0,
                "Z": 0.0,
                "W": -90.0
              },
              {
                "X": -1.0,
                "Y": 3.0,
                "Z": 0.0,
                "W": -90.0
              },
              {
                "X": 2.0,
                "Y": 2.0,
                "Z": 0.0,
                "W": -90.0
              },
              {
                "X": -2.0,
                "Y": 2.0,
                "Z": 0.0,
                "W": -90.0
              }
            ]
          }
        },
        {
          "Key": "enm_form_06_arena",
          "Value": {
            "ID": "enm_form_06_arena",
            "Placement": [
              {
                "X": 0.0,
                "Y": 2.0,
                "Z": 0.0,
                "W": -90.0
              },
              {
                "X": 0.0,
                "Y": 4.0,
                "Z": 0.0,
                "W": -90.0
              },
              {
                "X": 1.0,
                "Y": 3.0,
                "Z": 0.0,
                "W": -90.0
              },
              {
                "X": -1.0,
                "Y": 3.0,
                "Z": 0.0,
                "W": -90.0
              },
              {
                "X": 2.0,
                "Y": 2.0,
                "Z": 0.0,
                "W": -90.0
              },
              {
                "X": -2.0,
                "Y": 2.0,
                "Z": 0.0,
                "W": -90.0
              }
            ]
          }
        },
        {
          "Key": "enm_form_06_arena_02",
          "Value": {
            "ID": "enm_form_06_arena_02",
            "Placement": [
              {
                "X": 1.0,
                "Y": 2.0,
                "Z": 0.0,
                "W": -90.0
              },
              {
                "X": -1.0,
                "Y": 2.0,
                "Z": 0.0,
                "W": -90.0
              },
              {
                "X": 0.0,
                "Y": 4.0,
                "Z": 0.0,
                "W": -90.0
              },
              {
                "X": 0.0,
                "Y": 3.0,
                "Z": 0.0,
                "W": -90.0
              },
              {
                "X": 2.0,
                "Y": 3.0,
                "Z": 0.0,
                "W": -90.0
              },
              {
                "X": -2.0,
                "Y": 3.0,
                "Z": 0.0,
                "W": -90.0
              }
            ]
          }
        },
        {
          "Key": "enm_form_07_arena",
          "Value": {
            "ID": "enm_form_07_arena",
            "Placement": [
              {
                "X": 0.0,
                "Y": 2.0,
                "Z": 0.0,
                "W": -90.0
              },
              {
                "X": 1.0,
                "Y": 4.0,
                "Z": 0.0,
                "W": -90.0
              },
              {
                "X": 2.0,
                "Y": 3.0,
                "Z": 0.0,
                "W": -90.0
              },
              {
                "X": 3.0,
                "Y": 2.0,
                "Z": 0.0,
                "W": -90.0
              },
              {
                "X": -1.0,
                "Y": 4.0,
                "Z": 0.0,
                "W": -90.0
              },
              {
                "X": -2.0,
                "Y": 3.0,
                "Z": 0.0,
                "W": -90.0
              },
              {
                "X": -3.0,
                "Y": 2.0,
                "Z": 0.0,
                "W": -90.0
              }
            ]
          }
        },
        {
          "Key": "enm_form_07_arena_02",
          "Value": {
            "ID": "enm_form_07_arena_02",
            "Placement": [
              {
                "X": 0.0,
                "Y": 2.0,
                "Z": 0.0,
                "W": -90.0
              },
              {
                "X": 0.0,
                "Y": 3.0,
                "Z": 0.0,
                "W": -90.0
              },
              {
                "X": 1.0,
                "Y": 2.0,
                "Z": 0.0,
                "W": -90.0
              },
              {
                "X": -1.0,
                "Y": 2.0,
                "Z": 0.0,
                "W": -90.0
              },
              {
                "X": 0.0,
                "Y": 4.0,
                "Z": 0.0,
                "W": -90.0
              },
              {
                "X": 1.0,
                "Y": 3.0,
                "Z": 0.0,
                "W": -90.0
              },
              {
                "X": -1.0,
                "Y": 3.0,
                "Z": 0.0,
                "W": -90.0
              }
            ]
          }
        },
        {
          "Key": "enm_form_08_arena",
          "Value": {
            "ID": "enm_form_08_arena",
            "Placement": [
              {
                "X": 0.0,
                "Y": 4.0,
                "Z": 0.0,
                "W": -90.0
              },
              {
                "X": 0.0,
                "Y": 2.0,
                "Z": 0.0,
                "W": -90.0
              },
              {
                "X": 1.0,
                "Y": 3.0,
                "Z": 0.0,
                "W": -90.0
              },
              {
                "X": -1.0,
                "Y": 3.0,
                "Z": 0.0,
                "W": -90.0
              },
              {
                "X": 2.0,
                "Y": 4.0,
                "Z": 0.0,
                "W": -90.0
              },
              {
                "X": 2.0,
                "Y": 2.0,
                "Z": 0.0,
                "W": -90.0
              },
              {
                "X": -2.0,
                "Y": 4.0,
                "Z": 0.0,
                "W": -90.0
              },
              {
                "X": -2.0,
                "Y": 2.0,
                "Z": 0.0,
                "W": -90.0
              }
            ]
          }
        }
      ]
    }
  }
]